vosk/__init__.py
vosk/libgcc_s_sjlj-1.dll
vosk/libstdc++-6.dll
vosk/libvosk.dll
vosk/libwinpthread-1.dll
vosk/vosk_cffi.py
vosk/transcriber/__init__.py
vosk/transcriber/cli.py
vosk/transcriber/transcriber.py
vosk-0.3.44.dist-info/METADATA
vosk-0.3.44.dist-info/WHEEL
vosk-0.3.44.dist-info/entry_points.txt
vosk-0.3.44.dist-info/top_level.txt
vosk-0.3.44.dist-info/RECORD
