Metadata-Version: 2.0
Name: vosk
Version: 0.3.44
Summary: Offline open source speech recognition API based on Kaldi and Vosk
Home-page: https://github.com/alphacep/vosk-api
Author: Alpha Cephei Inc
Author-email: contact@alphacephei.com
License: UNKNOWN
Platform: UNKNOWN
Classifier: Programming Language :: Python :: 3
Classifier: License :: OSI Approved :: Apache Software License
Classifier: Operating System :: Microsoft :: Windows
Classifier: Operating System :: POSIX :: Linux
Classifier: Operating System :: MacOS :: MacOS X
Classifier: Topic :: Software Development :: Libraries :: Python Modules
Requires-Python: >=3
Requires-Dist: cffi (>=1.0)
Requires-Dist: requests
Requires-Dist: srt
Requires-Dist: tqdm
Requires-Dist: websockets
